traffic/traffic.py
webtraffic-0.5.3.dist-info/LICENSE
webtraffic-0.5.3.dist-info/METADATA
webtraffic-0.5.3.dist-info/WHEEL
webtraffic-0.5.3.dist-info/entry_points.txt
webtraffic-0.5.3.dist-info/top_level.txt
webtraffic-0.5.3.dist-info/RECORD
